{
  "0": [
    "iphone",
    "new",
    "review",
    "tech",
    "pro"
  ],
  "1": [
    "world",
    "world record",
    "record",
    "smallest",
    "keyboard"
  ],
  "2": [
    "laptop",
    "gaming",
    "gaming laptop",
    "new",
    "gaming laptops"
  ],
  "3": [
    "smartphone",
    "2025",
    "awards",
    "coolest smartphone",
    "new"
  ],
  "4": [
    "phone",
    "review",
    "folding phone",
    "folding",
    "phone case"
  ],
  "5": [
    "apple",
    "wan",
    "ai",
    "2026",
    "pro"
  ]
}